corecrud/__init__.py
corecrud/arguments.py
corecrud/collector.py
corecrud/main.py
corecrud/operations.py
corecrud/typing.py
corecrud/utils.py
corecrud/cursors/__init__.py
corecrud/cursors/abc.py
corecrud/cursors/mapping.py
corecrud/cursors/scalars.py
corecrud-0.1.4.2.dist-info/METADATA
corecrud-0.1.4.2.dist-info/WHEEL
corecrud-0.1.4.2.dist-info/licenses/LICENSE
corecrud-0.1.4.2.dist-info/RECORD
